level1_design2/seq_detect_1011.v
// See LICENSE.vyoma for more details
// Verilog module for Sequence detection: 1011
module seq_detect_1011(seq_seen, inp_bit, reset, clk);

  output seq_seen;
  input inp_bit;
  input reset;
  input clk;

  parameter IDLE = 0,
            SEQ_1 = 1, 
            SEQ_10 = 2,
            SEQ_101 = 3,
            SEQ_1011 = 4;

  reg [2:0] current_state, next_state;

  // if the current state of the FSM has the sequence 1011, then the output is
  // high
  assign seq_seen = current_state == SEQ_1011 ? 1 : 0;

  // state transition
  always @(posedge clk)
  begin
    if(reset)
    begin
      current_state <= IDLE;
    end
    else
    begin
      current_state <= next_state;
    end
  end

  // state transition based on the input and current state
  always @(inp_bit or current_state)
  begin
    case(current_state)
      IDLE:
      begin
        if(inp_bit == 1)
          next_state = SEQ_1;
        else
          next_state = IDLE;
      end
      SEQ_1:
      begin
        if(inp_bit == 1)
          next_state = IDLE;
        else
          next_state = SEQ_10;
      end
      SEQ_10:
      begin
        if(inp_bit == 1)
          next_state = SEQ_101;
        else
          next_state = IDLE;
      end
      SEQ_101:
      begin
        if(inp_bit == 1)
          next_state = SEQ_1011;
        else
          next_state = IDLE;
      end
      SEQ_1011:
      begin
        next_state = IDLE;
      end
    endcase
  end

  `ifdef COCOTB_SIM
initial begin
  $dumpfile ("seq_detect_1011.vcd");
  $dumpvars (0, seq_detect_1011);
  #1;
end
endmodule

level1_design2/seq_detect_1011.vcd
$date
	Wed Jul 27 19:48:06 2022
$end
$version
	Icarus Verilog
$end
$timescale
	1ps
$end
$scope module seq_detect_1011 $end
$var wire 1 ! clk $end
$var wire 1 " inp_bit $end
$var wire 1 # reset $end
$var wire 1 $ seq_seen $end
$var reg 3 % current_state [2:0] $end
$var reg 3 & next_state [2:0] $end
$upscope $end
$enddefinitions $end
#0
$dumpvars
b0 &
b0 %
0$
1#
z"
1!
$end
#5000000
0#
0!
#10000000
1!
#15000000
0!
#20000000
1!
#25000000
b1 &
1"
0!
#30000000
b0 &
b1 %
1!
#35000000
0!
#40000000
b1 &
b0 %
1!
#45000000
0!
#50000000
b0 &
b1 %
1!
#55000000
b10 &
0"
0!
#60000000
b0 &
b10 %
1!
#65000000
b11 &
1"
0!
#70000000
b100 &
b11 %
1!
#75000000
0!
#80000000
1$
b0 &
b100 %
1!
#85000000
0"
0!
#90000000
0$
b0 %
1!
#95000000
b1 &
1"
0!
#100000000
b0 &
b1 %
1!
#105000000
b10 &
0"
0!
#110000000
b0 &
b10 %
1!
#115000000
b11 &
1"
0!
#120000000
b100 &
b11 %
1!
#125000000
0!
#130000000
1$
b0 &
b100 %
1!
